mcp_server_qiwei/__init__.py
mcp_server_qiwei/app_config.py
mcp_server_qiwei/qwei_client.py
mcp_server_qiwei/server.py
mcp_server_qiwei-0.2.2.dist-info/METADATA
mcp_server_qiwei-0.2.2.dist-info/WHEEL
mcp_server_qiwei-0.2.2.dist-info/entry_points.txt
mcp_server_qiwei-0.2.2.dist-info/top_level.txt
mcp_server_qiwei-0.2.2.dist-info/RECORD
