Metadata-Version: 2.4
Name: mcp-server-qiwei
Version: 0.2.2
Summary: Qiwei MCP Server
Author-email: ryanjhzheng <zhengjianhong95@gmail.com>
Keywords: mcp,qiwei
Requires-Python: >=3.13
Requires-Dist: httpx
Requires-Dist: requests
Requires-Dist: mcp[cli]>=1.0.0
